{"cameraMode":{"drawMode":0,"name":"Shaded","section":"Shading Mode"},"sceneLighting":true,"audioPlay":false,"sceneViewState":{"m_AlwaysRefresh":false,"showFog":true,"showSkybox":true,"showFlares":true,"showImageEffects":true,"showParticleSystems":true,"showVisualEffectGraphs":true,"m_FxEnabled":true},"in2DMode":false,"pivot":{"x":-0.011094232089817524,"y":0.07419931888580322,"z":0.6904932856559753},"rotation":{"x":-0.004505120683461428,"y":0.017991526052355768,"z":-0.00019706544117070735,"w":-0.9998854994773865},"size":0.25586843490600588,"orthographic":false}